upb/__init__.py
upb/client.py
upb/const.py
upb/device.py
upb/memory.py
upb/protocol.py
upb/register.py
upb/util.py
upb/tools/dumpreg.py
upb-0.0.3.dist-info/LICENSE
upb-0.0.3.dist-info/METADATA
upb-0.0.3.dist-info/WHEEL
upb-0.0.3.dist-info/top_level.txt
upb-0.0.3.dist-info/RECORD
